webworld/__init__.py
webworld/envs/__init__.py
webworld/envs/web_world.py
webworld-0.0.0.dist-info/LICENSE
webworld-0.0.0.dist-info/METADATA
webworld-0.0.0.dist-info/WHEEL
webworld-0.0.0.dist-info/top_level.txt
webworld-0.0.0.dist-info/RECORD
